{
  "category": "device.router",
  "description": "Nokia SRLinux Router - leaf2",
  "name": "srlinux-leaf2",
  "serialNumber": "SRL-7220-IXR-D2L-2024-002",
  "resourceCharacteristic": [
    {
      "name": "vendor",
      "value": "Nokia"
    },
    {
      "name": "model",
      "value": "7220 IXR-D2L"
    },
    {
      "name": "os-version",
      "value": "24.10.1"
    },
    {
      "name": "management-ip",
      "value": "172.80.80.12"
    },
    {
      "name": "site",
      "value": "Site-B"
    },
    {
      "name": "interface-ethernet-1/1",
      "value": "up"
    },
    {
      "name": "interface-ethernet-1/49",
      "value": "up"
    }
  ],
  "@type": "PhysicalResource",
  "@schemaLocation": "https://bitbucket.software.geant.org/projects/OSSBSS/repos/maat-schema/raw/TMF639-ResourceInventory-v4-pionier.json"
}